setup.cfg
setup.py
PyLogStash/PyLogStash.py
PyLogStash/__init__.py
PyLogStash.egg-info/PKG-INFO
PyLogStash.egg-info/SOURCES.txt
PyLogStash.egg-info/dependency_links.txt
PyLogStash.egg-info/requires.txt
PyLogStash.egg-info/top_level.txt