Metadata-Version: 1.0
Name: PyLogStash
Version: 0.0.2
Summary: Pacote de integração Http com o logstash
Home-page: http://git.fortbrasil.com.br/Dev/PyLogStash.git
Author: pedro.nascimento
Author-email: pedro.nascimento@fortbrasil.com.br
License: MIT License
Keywords: logstash fortbrasil
Platform: UNKNOWN
